<manifest alg="2" build="5" opt="false" iceEnabled="true">
  <folder name="css">
    <file name="site_global.css" crc="3983832653"/>
    <file name="master_a-master.css" crc="489304487" ref="index:customplan:getstarted:customplan-copy"/>
    <file name="index.css" crc="4162747114" ref="index"/>
    <file name="iefonts_index.css" crc="4156482367" ref="index"/>
    <file name="customplan.css" crc="476911626" ref="customplan"/>
    <file name="iefonts_customplan.css" crc="366592594" ref="customplan"/>
    <file name="getstarted.css" crc="4005394035" ref="getstarted"/>
    <file name="iefonts_getstarted.css" crc="3783769575" ref="getstarted"/>
    <file name="customplan-copy.css" crc="8968429" ref="customplan-copy"/>
    <file name="iefonts_customplan-copy.css" crc="3956008729" ref="customplan-copy"/>
  </folder>
  <folder name="scripts">
    <file name="jquery-1.8.3.min.js" crc="209076791" ref="index:getstarted:customplan:customplan-copy"/>
    <file name="museutils.js" crc="4291592202" ref="index:getstarted:customplan:customplan-copy"/>
    <file name="pie.js" crc="3827607177" ref="index:getstarted:customplan:customplan-copy"/>
    <file name="jquery.tobrowserwidth.js" crc="3842421675" ref="index:getstarted:customplan:customplan-copy"/>
    <file name="webpro.js" crc="3903299128" ref="index:getstarted:customplan:customplan-copy"/>
    <file name="musewpslideshow.js" crc="138381373" ref="index:getstarted:customplan:customplan-copy"/>
    <file name="jquery.museoverlay.js" crc="4250894771" ref="index:getstarted:customplan:customplan-copy"/>
    <file name="touchswipe.js" crc="4156838003" ref="index:getstarted:customplan:customplan-copy"/>
    <file name="jquery.musepolyfill.bgsize.js" crc="291134478" ref="index"/>
    <file name="jquery.watch.js" crc="4068933136" ref="index:getstarted:customplan:customplan-copy"/>
    <file name="musewpdisclosure.js" crc="4285748861" ref="customplan-copy"/>
  </folder>
  <folder name="images">
    <file name="apex-financial-logo.png" crc="342918202" ref="index"/>
    <file name="u1108-4-full.png" crc="449055638" ref="index:getstarted:customplan:customplan-copy"/>
    <file name="u1108-4-r-full.png" crc="506129933" ref="index:getstarted:customplan:customplan-copy"/>
    <file name="u293-full.png" crc="3947769652" ref="index:getstarted:customplan:customplan-copy"/>
    <file name="telephone.png" crc="4245745487" ref="index"/>
    <file name="u304-4-full.png" crc="3913702143" ref="index:getstarted:customplan:customplan-copy"/>
    <file name="u304-4-r-full.png" crc="3852178714" ref="index:getstarted:customplan:customplan-copy"/>
    <file name="happy2.jpg" crc="3864659057" ref="index"/>
    <file name="u1015-4-full.png" crc="395407738" ref="index"/>
    <file name="u1015-4-r-full.png" crc="4201973118" ref="index"/>
    <file name="gold.png" crc="47475718" ref="index"/>
    <file name="handshake.png" crc="10988271" ref="index"/>
    <file name="affordable.png" crc="109019593" ref="index"/>
    <file name="u1367-4-full.png" crc="167480672" ref="index"/>
    <file name="u1367-4-r-full.png" crc="443221253" ref="index"/>
    <file name="apex-financial-logo-u316-fr.png" crc="4237683419" ref="index"/>
    <file name="telephone-u325-fr.png" crc="226170209" ref="index"/>
    <file name="verisign.png" crc="4225892542" ref="index"/>
    <file name="truste.png" crc="53826659" ref="index"/>
    <file name="portfoliomanager.png" crc="4257163445" ref="getstarted:customplan:customplan-copy"/>
    <file name="youwhite.png" crc="183414670" ref="getstarted"/>
    <file name="arrowright-u1204-fr.png" crc="36767710" ref="getstarted:customplan:customplan-copy"/>
    <file name="profile.png" crc="86876344" ref="getstarted:customplan"/>
    <file name="portfolio.png" crc="105560921" ref="getstarted:customplan-copy"/>
    <file name="u1157-4-full.png" crc="3766052987" ref="getstarted"/>
    <file name="u1157-4-r-full.png" crc="4265305988" ref="getstarted"/>
    <file name="checkwhite.png" crc="238540841" ref="getstarted"/>
    <file name="pie.png" crc="301302250" ref="customplan"/>
    <file name="u1363-4-full.png" crc="168034125" ref="customplan"/>
    <file name="u1363-4-r-full.png" crc="3901046465" ref="customplan"/>
    <file name="save.png" crc="4039863783" ref="customplan"/>
    <file name="share.png" crc="3891941752" ref="customplan"/>
    <file name="you.png" crc="3828573718" ref="customplan:customplan-copy"/>
    <file name="portfoliowhite.png" crc="448522854" ref="customplan"/>
    <file name="u1361-4-full.png" crc="3969743172" ref="customplan"/>
    <file name="u1361-4-r-full.png" crc="4120104692" ref="customplan"/>
    <file name="accountwhite.png" crc="3982954835" ref="customplan-copy"/>
    <file name="stripe.png" crc="434306932" ref="customplan-copy"/>
    <file name="visalogo.png" crc="4011762262" ref="customplan-copy"/>
    <file name="mastercar.png" crc="78992415" ref="customplan-copy"/>
    <file name="wiretransfer.png" crc="79172768" ref="customplan-copy"/>
    <file name="u1776-4-full.png" crc="465261218" ref="customplan-copy"/>
    <file name="u1776-4-r-full.png" crc="151470120" ref="customplan-copy"/>
    <file name="u1780-4-full.png" crc="3815976541" ref="customplan-copy"/>
    <file name="u1780-4-r-full.png" crc="122438712" ref="customplan-copy"/>
  </folder>
  <file name="index.html" crc="3884407758" mt="1403250629730" redirect="true"/>
  <file name="getstarted.html" crc="3961695755" mt="1403250629732" redirect="true"/>
  <file name="customplan.html" crc="4109216407" mt="1403250629740" redirect="true"/>
  <file name="customplan-copy.html" crc="3922019471" mt="1403251269677" redirect="true"/>
</manifest>